django_deepl/__init__.py
django_deepl/admin.py
django_deepl/apps.py
django_deepl/models.py
django_deepl/tests.py
django_deepl/utils.py
django_deepl/views.py
django_deepl/management/__init__.py
django_deepl/management/commands/__init__.py
django_deepl/management/commands/check_translations_status.py
django_deepl/management/commands/clean_empty_translations.py
django_deepl/management/commands/clean_obsolete_translations.py
django_deepl/management/commands/delete_backups.py
django_deepl/management/commands/translate.py
django_deepl-0.0.5.dist-info/licenses/LICENSE
django_deepl-0.0.5.dist-info/METADATA
django_deepl-0.0.5.dist-info/WHEEL
django_deepl-0.0.5.dist-info/top_level.txt
django_deepl-0.0.5.dist-info/RECORD
