Metadata-Version: 2.4
Name: django-deepl
Version: 0.0.5
Summary: Django app to translate .po files using DeepL translation service
Home-page: https://github.com/iTz-i-Soldier/django-deepl
Author: iTz-i-Soldier
Author-email: iTz-i-Soldier@users.noreply.github.com
Classifier: Programming Language :: Python :: 3
Classifier: Programming Language :: Python :: 3.8
Classifier: Programming Language :: Python :: 3.9
Classifier: License :: OSI Approved :: MIT License
Classifier: Operating System :: OS Independent
Requires-Python: >=3.6
License-File: LICENSE
Requires-Dist: Django>=3.0
Requires-Dist: polib==1.2.0
Requires-Dist: deepl==1.21.0
Dynamic: author
Dynamic: author-email
Dynamic: classifier
Dynamic: description
Dynamic: description-content-type
Dynamic: home-page
Dynamic: license-file
Dynamic: requires-dist
Dynamic: requires-python
Dynamic: summary
